AUTHORS.rst
CONTRIBUTING.rst
HISTORY.rst
LICENSE
MANIFEST.in
README.rst
setup.cfg
setup.py
docs/Makefile
docs/authors.rst
docs/conf.py
docs/contributing.rst
docs/history.rst
docs/index.rst
docs/installation.rst
docs/make.bat
docs/quickstart.rst
docs/readme.rst
docs/usage.rst
docs/dist/_static/file.png
docs/dist/_static/minus.png
docs/dist/_static/plus.png
electrochem/__init__.py
electrochem/_version.py
electrochem/cli.py
electrochem/electrochem.py
electrochem/parse.py
electrochem/parse_gui.py
electrochem.egg-info/PKG-INFO
electrochem.egg-info/SOURCES.txt
electrochem.egg-info/dependency_links.txt
electrochem.egg-info/entry_points.txt
electrochem.egg-info/not-zip-safe
electrochem.egg-info/requires.txt
electrochem.egg-info/top_level.txt
electrochem/modules/MainWindow.py
electrochem/modules/__init__.py
electrochem/modules/display.py
electrochem/modules/errors.py
electrochem/modules/extractRes.py
electrochem/modules/gui_interact.py
electrochem/modules/utils.py
tests/__init__.py
tests/test_electrochem.py